proy/__init__.py
proy-0.1.4.dist-info/LICENSE.txt
proy-0.1.4.dist-info/METADATA
proy-0.1.4.dist-info/WHEEL
proy-0.1.4.dist-info/top_level.txt
proy-0.1.4.dist-info/RECORD
